{"Untitled":{"slug":"Untitled","filePath":"Untitled.md","title":"Untitled","links":["liens-internes"],"tags":["projets","en","cours"],"content":"index\nVoici une note minimale pour Quartz.\nElle est prête à être reliée à d’autres notes via liens internes."},"archives/index":{"slug":"archives/index","filePath":"archives/index.md","title":"Titre de la note","links":["liens-internes"],"tags":["projets","en-cours"],"content":"Titre de la note\nVoici une note minimale pour Quartz.\nElle est prête à être reliée à d’autres notes via liens internes."},"index":{"slug":"index","filePath":"index.md","title":"Je note donc je suis","links":["notes/zones","notes/ressources"],"tags":["index","accueil"],"content":"Bienvenue dans ce jardin numérique\nà ma montre pas Seiko il est exactement 21 h 34 -\nIci, vous trouverez un récapitulatif des projets en cours dans le jardin numérique. Chaque projet est relié à d’autres notes pertinentes dans le jardin. Il sera question de zones, de ressources, de projets et d’archives.\nPar exemple, il y aura des ressources.\nQu’est-ce que c’est un jardin numérique  :\nPas la peine de tourner vers wikipédia pour le savoir, j’ai tenté de créer une page à ce sujet mais les gardiens du temple du savoir semble avoir un a priori négatif à propos de ce dont ils n’ont jamais entendu parler.\nQu’est-ce que ça n’est pas ?\nUn blog\nLe contenu n’est pas organisé par le plus récent qui s’affiche en premier. Pas moyen de lâcher ton comm’. Si Quartz offre la possibilité d’insérer des images, je ne l’ai pas encore trouvée.\n\nÀ suivre\nLe contenu sera ajouté au fur et à mesure. Reviens souvent !"},"notes/index":{"slug":"notes/index","filePath":"notes/index.md","title":"Projets","links":[],"tags":["projets","index"],"content":"Bienvenue au jardin\n\nProjets à venir\nLes projets à venir seront ajoutés prochainement."},"notes/ressources":{"slug":"notes/ressources","filePath":"notes/ressources.md","title":"Ressources","links":[],"tags":["ressources","index"],"content":"Bienvenue dans le hangar à ressources\n"},"notes/zones":{"slug":"notes/zones","filePath":"notes/zones.md","title":"Zones","links":[],"tags":["zones","index"],"content":"Zones ! zones !\nZone écriture\nZone internet"}}